LayerClient/LayerClient.py
LayerClient/__init__.py
LayerClient-0.1.10.dist-info/DESCRIPTION.rst
LayerClient-0.1.10.dist-info/METADATA
LayerClient-0.1.10.dist-info/RECORD
LayerClient-0.1.10.dist-info/WHEEL
LayerClient-0.1.10.dist-info/metadata.json
LayerClient-0.1.10.dist-info/top_level.txt
