Metadata-Version: 2.0
Name: LayerClient
Version: 0.1.10
Summary: Client for the Layer Platform API
Home-page: https://github.com/Jana-Mobile/layer-python
Author: Jana
Author-email: opensource@jana.com
License: Apache 2.0
Platform: UNKNOWN
Classifier: Development Status :: 3 - Alpha
Classifier: Intended Audience :: Developers
Classifier: Topic :: Software Development :: Libraries :: Python Modules
Classifier: License :: OSI Approved :: Apache Software License
Classifier: Programming Language :: Python :: 2.6
Classifier: Programming Language :: Python :: 2.7
Classifier: Programming Language :: Python :: 3
Requires-Dist: python-dateutil
Requires-Dist: requests
